XNAT_CLI_Toolkit/__init__.py
XNAT_CLI_Toolkit/archive_to_xnat.py
XNAT_CLI_Toolkit/authenticate.py
XNAT_CLI_Toolkit/commands.py
XNAT_CLI_Toolkit/list.py
XNAT_CLI_Toolkit/share.py
XNAT_CLI_Toolkit/update_demographics.py
XNAT_CLI_Toolkit/upload_to_prearchive.py
XNAT_CLI_Toolkit/xnat_upload.py
XNAT_CLI_Toolkit-0.5.1.dist-info/LICENSE.txt
XNAT_CLI_Toolkit-0.5.1.dist-info/METADATA
XNAT_CLI_Toolkit-0.5.1.dist-info/WHEEL
XNAT_CLI_Toolkit-0.5.1.dist-info/entry_points.txt
XNAT_CLI_Toolkit-0.5.1.dist-info/top_level.txt
XNAT_CLI_Toolkit-0.5.1.dist-info/RECORD
