Metadata-Version: 2.1
Name: XNAT_CLI_Toolkit
Version: 0.5.1
Summary: A collection of scripts for sharing/uploading and listing data from XNAT repositories.
Home-page: 
Author: Rahul Rajput
Author-email: rahul.rajput@proxmed.com.au
License: The MIT License (MIT)
Classifier: Development Status :: 4 - Beta
Classifier: Intended Audience :: Healthcare Industry
Classifier: Intended Audience :: Science/Research
Classifier: License :: OSI Approved :: Apache Software License
Classifier: Natural Language :: English
Classifier: Programming Language :: Python :: 3.4
Classifier: Programming Language :: Python :: 3.5
Classifier: Programming Language :: Python :: 3.6
Classifier: Programming Language :: Python :: 3.7
Classifier: Programming Language :: Python :: 3.8
Classifier: Topic :: Scientific/Engineering :: Bio-Informatics
Classifier: Topic :: Scientific/Engineering :: Medical Science Apps.
Requires-Python: >=3.4
License-File: LICENSE.txt
Requires-Dist: xnat>=0.6
Requires-Dist: progressbar2>=3.16.0
Requires-Dist: future>=0.16
